pecs/__init__.py
pecs/component.py
pecs/entity.py
pecs/system.py
pecs/world.py
test/main.py
peach_ecs-0.0.6.dist-info/METADATA
peach_ecs-0.0.6.dist-info/WHEEL
peach_ecs-0.0.6.dist-info/top_level.txt
peach_ecs-0.0.6.dist-info/RECORD
