Metadata-Version: 2.2
Name: peach-ecs
Version: 0.0.6
Author-email: Peach <james@christhall.us>
Project-URL: Homepage, https://gitlab.com/peach_experiments/pecs
Requires-Python: >=3.10
